<?xml version="1.0" encoding="UTF-8"?>
<metadata>
  <mediatype>audio</mediatype>
  <identifier>mtk001</identifier>
  <type>sound</type>
  <publicdate>2003-07-07 15:37:36</publicdate>
  <description>All the way from Alaska, Jiva provides us with some truly serene idm in the style of the similarly remote but moving Boards Of Canada or Biosphere. Beautiful home listening for everyone, and well worth the download. And we know our French is schoolboy at best, but the title is definitely something about strolling across the seabed, isn't it?</description>
  <licenseurl>http://creativecommons.org/licenses/by-nd-nc/1.0/</licenseurl>
  <date>0000-00-00 00:00:00</date>
  <title>Jiva - Sous L'Eau A Pied [mtk001]</title>
  <uploader>h0l@mono211.com</uploader>
  <addeddate>2003-07-07 15:37:36</addeddate>
  <adder>simon c</adder>
  <pick>0</pick>
  <updatedate>2003-07-07 16:42:55</updatedate>
  <updater>simon c</updater>
  <public>1</public>
  <subject>Electronic;IDM</subject>
  <numeric_id>299</numeric_id>
  <collection>monotonik</collection>
  <collection>netlabels</collection>
  <filesxml>Wed Sep 17 0:47:37 UTC 2014</filesxml>
  <boxid>OL100020605</boxid>
  <album>Sous l'eau a pied</album>
  <artist>Jiva</artist>
  <external-identifier>urn:mb_releasegroup_id:a9e3bdfe-e1d7-39fc-92df-6e9f60247d1f</external-identifier>
  <external-identifier>urn:mb_release_id:78c5b96d-5a76-480a-9428-a8b8991f8dde</external-identifier>
</metadata>
